MANIFEST.in
README
setup.py
Mambu.egg-info/PKG-INFO
Mambu.egg-info/SOURCES.txt
Mambu.egg-info/dependency_links.txt
Mambu.egg-info/requires.txt
Mambu.egg-info/top_level.txt
mambu/__init__.py
mambu/api.py
mambu/config.py
mambu/exception.py
mambu/etc/data.yaml
mambu/tools/__init__.py
mambu/tools/calendars.py
mambu/tools/datelib.py