Metadata-Version: 1.0
Name: Mambu
Version: 0.0.20
Summary: Python module for Mambu API
Home-page: https://www.mambu.com
Author: Paze.me Limited
Author-email: hansel.dunlop@paze.me
License: UNKNOWN
Platform: UNKNOWN
